pyams_content_es/__init__.py
pyams_content_es/document.py
pyams_content_es/include.py
pyams_content_es/interfaces.py
pyams_content_es/process.py
pyams_content_es/utility.py
pyams_content_es/utils.py
pyams_content_es/component/__init__.py
pyams_content_es/component/cards.py
pyams_content_es/component/contact.py
pyams_content_es/component/extfile.py
pyams_content_es/component/frame.py
pyams_content_es/component/gallery.py
pyams_content_es/component/illustration.py
pyams_content_es/component/keynumber.py
pyams_content_es/component/links.py
pyams_content_es/component/map.py
pyams_content_es/component/paragraph.py
pyams_content_es/component/thesaurus.py
pyams_content_es/component/video.py
pyams_content_es/component/workflow.py
pyams_content_es/doctests/README.rst
pyams_content_es/filter/__init__.py
pyams_content_es/filter/processor.py
pyams_content_es/generations/__init__.py
pyams_content_es/locales/pyams_content_es.pot
pyams_content_es/locales/fr/LC_MESSAGES/pyams_content_es.mo
pyams_content_es/locales/fr/LC_MESSAGES/pyams_content_es.po
pyams_content_es/scripts/__init__.py
pyams_content_es/shared/__init__.py
pyams_content_es/shared/view/__init__.py
pyams_content_es/shared/view/interfaces.py
pyams_content_es/shared/view/reference.py
pyams_content_es/shared/view/thesaurus.py
pyams_content_es/tests/__init__.py
pyams_content_es/tests/test_utilsdocs.py
pyams_content_es/tests/test_utilsdocstrings.py
pyams_content_es/zmi/__init__.py
pyams_content_es/zmi/content.py
pyams_content_es/zmi/dashboard.py
pyams_content_es/zmi/search.py
pyams_content_es/zmi/templates/test-indexer.pt
pyams_content_es-2.3.0.dist-info/LICENSE
pyams_content_es-2.3.0.dist-info/METADATA
pyams_content_es-2.3.0.dist-info/WHEEL
pyams_content_es-2.3.0.dist-info/entry_points.txt
pyams_content_es-2.3.0.dist-info/namespace_packages.txt
pyams_content_es-2.3.0.dist-info/top_level.txt
pyams_content_es-2.3.0.dist-info/RECORD
