Metadata-Version: 2.1
Name: pyams-content-es
Version: 2.3.0
Summary: Elasticsearch integration package for PyAMS content
Home-page: https://pyams.readthedocs.io
Author: Thierry Florac
Author-email: tflorac@ulthar.net
License: ZPL
Keywords: Pyramid PyAMS
Classifier: License :: OSI Approved :: Zope Public License
Classifier: Development Status :: 4 - Beta
Classifier: Programming Language :: Python
Classifier: Framework :: Pyramid
Classifier: Topic :: Software Development :: Libraries :: Python Modules
License-File: LICENSE
Requires-Dist: setuptools
Requires-Dist: elasticsearch
Requires-Dist: elasticsearch-dsl
Requires-Dist: persistent
Requires-Dist: pyams-catalog
Requires-Dist: pyams-content >=2.0.0
Requires-Dist: pyams-elastic
Requires-Dist: pyams-form >=2.1.0
Requires-Dist: pyams-i18n
Requires-Dist: pyams-layer
Requires-Dist: pyams-security
Requires-Dist: pyams-sequence
Requires-Dist: pyams-site
Requires-Dist: pyams-skin
Requires-Dist: pyams-table
Requires-Dist: pyams-template
Requires-Dist: pyams-thesaurus
Requires-Dist: pyams-utils >2.1.0
Requires-Dist: pyams-viewlet
Requires-Dist: pyams-workflow
Requires-Dist: pyams-zmi
Requires-Dist: pyams-zmq
Requires-Dist: pyramid
Requires-Dist: transaction
Requires-Dist: zope.annotation
Requires-Dist: zope.container
Requires-Dist: zope.dublincore
Requires-Dist: zope.interface
Requires-Dist: zope.intid
Requires-Dist: zope.lifecycleevent
Requires-Dist: zope.schema
Provides-Extra: test
Requires-Dist: pyramid-zcml ; extra == 'test'
Requires-Dist: zope.exceptions ; extra == 'test'
